thoraxe/__init__.py
thoraxe/thoraxe.py
thoraxe/version.py
thoraxe/add_transcripts/__init__.py
thoraxe/add_transcripts/add_transcripts.py
thoraxe/subexons/__init__.py
thoraxe/subexons/alignment.py
thoraxe/subexons/ases.py
thoraxe/subexons/graph.py
thoraxe/subexons/phylosofs.py
thoraxe/subexons/plot.py
thoraxe/subexons/rescue.py
thoraxe/subexons/subexons.py
thoraxe/subexons/tidy.py
thoraxe/subexons/assets/cluster_plots.html
thoraxe/transcript_info/__init__.py
thoraxe/transcript_info/clusters.py
thoraxe/transcript_info/exon_clustering.py
thoraxe/transcript_info/phases.py
thoraxe/transcript_info/transcript_info.py
thoraxe/transcript_query/__init__.py
thoraxe/transcript_query/transcript_query.py
thoraxe/utils/__init__.py
thoraxe/utils/folders.py
thoraxe/utils/species.py
thoraxe/utils/split.py
thoraxe/utils/windows.py
thoraxe-0.8.3.dist-info/LICENSE
thoraxe-0.8.3.dist-info/METADATA
thoraxe-0.8.3.dist-info/WHEEL
thoraxe-0.8.3.dist-info/entry_points.txt
thoraxe-0.8.3.dist-info/top_level.txt
thoraxe-0.8.3.dist-info/RECORD
